vidutils/__init__.py
vidutils-0.0.0.dist-info/LICENSE
vidutils-0.0.0.dist-info/METADATA
vidutils-0.0.0.dist-info/WHEEL
vidutils-0.0.0.dist-info/RECORD
