Metadata-Version: 2.1
Name: vidutils
Version: 0.0.0
Summary: Video processing tools for prototyping in Python.
Author: Riccardo Lincetto
Author-email: 37301469+RiccardoLincetto@users.noreply.github.com
Requires-Python: >=3.11,<4.0
Classifier: Programming Language :: Python :: 3
Classifier: Programming Language :: Python :: 3.11
